{
    "Status-Code": 200,
    "Connection": "keep-alive",
    "Content-Length": "727",
    "Server": "GitHub.com",
    "Content-Type": "text/plain; charset=utf-8",
    "Last-Modified": "Wed, 10 Aug 2016 19:00:16 GMT",
    "Access-Control-Allow-Origin": "*",
    "ETag": "W/\"57ab79c0-5d1\"",
    "expires": "Sat, 04 Oct 2025 20:14:39 GMT",
    "Cache-Control": "max-age=600",
    "Content-Encoding": "gzip",
    "x-proxy-cache": "MISS",
    "X-GitHub-Request-Id": "2294:1BBE:E8760D:10A6B04:68E17DD7",
    "Accept-Ranges": "bytes",
    "Age": "0",
    "Date": "Sat, 04 Oct 2025 20:04:39 GMT",
    "Via": "1.1 varnish",
    "X-Served-By": "cache-yvr1521-YVR",
    "X-Cache": "MISS",
    "X-Cache-Hits": "0",
    "X-Timer": "S1759608279.432901,VS0,VE115",
    "Vary": "Accept-Encoding",
    "X-Fastly-Request-ID": "3a87265741441b6e5ab1ef64159c4cbb2289a1f3"
}